django_expiring_token/__init__.py
django_expiring_token/admin.py
django_expiring_token/apps.py
django_expiring_token/authentication.py
django_expiring_token/models.py
django_expiring_token/serializers.py
django_expiring_token/settings.py
django_expiring_token/urls.py
django_expiring_token/views.py
django_expiring_token/migrations/0001_initial.py
django_expiring_token/migrations/0002_auto_20210310_2043.py
django_expiring_token/migrations/__init__.py
django_expiring_token-1.0.3.dist-info/LICENSE
django_expiring_token-1.0.3.dist-info/METADATA
django_expiring_token-1.0.3.dist-info/WHEEL
django_expiring_token-1.0.3.dist-info/top_level.txt
django_expiring_token-1.0.3.dist-info/RECORD
