Metadata-Version: 2.1
Name: django-expiring-token
Version: 1.0.3
Summary: Expiring token with expiration time update for Django Rest Framework
Home-page: https://github.com/KlemenS189/django-expiring-token
Author: Klemen Štrajhar
Author-email: klemen.strajhar@gmail.si
License: MIT License
Platform: UNKNOWN
Classifier: Development Status :: 5 - Production/Stable
Classifier: Environment :: Web Environment
Classifier: Framework :: Django
Classifier: Intended Audience :: Developers
Classifier: License :: OSI Approved :: MIT License
Classifier: Operating System :: OS Independent
Classifier: Programming Language :: Python
Classifier: Programming Language :: Python :: 3.4
Classifier: Programming Language :: Python :: 3.5
Classifier: Programming Language :: Python :: 3.6
Classifier: Framework :: Django :: 2.0
Classifier: Framework :: Django :: 2.1
Classifier: Topic :: Internet :: WWW/HTTP
License-File: LICENSE
Requires-Dist: djangorestframework >=3.4.0
